test_calculator/__init__.py
test_calculator/operations.py
abc_test_code-0.1.0.dist-info/LICENSE
abc_test_code-0.1.0.dist-info/METADATA
abc_test_code-0.1.0.dist-info/WHEEL
abc_test_code-0.1.0.dist-info/top_level.txt
abc_test_code-0.1.0.dist-info/RECORD
