Metadata-Version: 2.1
Name: abc-test-code
Version: 0.1.0
Summary: A simple calculator package for arithmetic operations.
Home-page: https://github.com/akash-verma998/calculator
Author: nicecode
Author-email: akash.verma1076@gmail.com
License: UNKNOWN
Platform: UNKNOWN
Classifier: Programming Language :: Python :: 3
Classifier: License :: OSI Approved :: MIT License
Classifier: Operating System :: OS Independent
Requires-Python: >=3.7
License-File: LICENSE
